setup.py
focusployer/__init__.py
focusployer/deployer.py
focusployer.egg-info/PKG-INFO
focusployer.egg-info/SOURCES.txt
focusployer.egg-info/dependency_links.txt
focusployer.egg-info/requires.txt
focusployer.egg-info/top_level.txt