Metadata-Version: 2.1
Name: focusployer
Version: 1.1.1
Author: uni
Requires-Dist: asyncssh
Requires-Dist: loguru
